main/architect.py
architect_cli-0.1.4.dist-info/METADATA
architect_cli-0.1.4.dist-info/WHEEL
architect_cli-0.1.4.dist-info/entry_points.txt
architect_cli-0.1.4.dist-info/top_level.txt
architect_cli-0.1.4.dist-info/RECORD
