Metadata-Version: 2.4
Name: architect-cli
Version: 0.1.4
Summary: A command-line tool to build file structures from text and scan directories.
Author-email: mhdgning131 <gningmoustapha078@gmail.com>
Project-URL: Homepage, https://github.com/mhdgning131/Architect
Project-URL: Issues, https://github.com/mhdgning131/Architect/issues
Classifier: Programming Language :: Python :: 3
Classifier: License :: OSI Approved :: MIT License
Classifier: Operating System :: OS Independent
Classifier: Topic :: System :: Filesystems
Classifier: Topic :: Utilities
Requires-Python: >=3.7
